google/cloud/osconfig/__init__.py
google/cloud/osconfig/gapic_version.py
google/cloud/osconfig/py.typed
google/cloud/osconfig_v1/__init__.py
google/cloud/osconfig_v1/gapic_metadata.json
google/cloud/osconfig_v1/gapic_version.py
google/cloud/osconfig_v1/py.typed
google/cloud/osconfig_v1/services/__init__.py
google/cloud/osconfig_v1/services/os_config_service/__init__.py
google/cloud/osconfig_v1/services/os_config_service/async_client.py
google/cloud/osconfig_v1/services/os_config_service/client.py
google/cloud/osconfig_v1/services/os_config_service/pagers.py
google/cloud/osconfig_v1/services/os_config_service/transports/__init__.py
google/cloud/osconfig_v1/services/os_config_service/transports/base.py
google/cloud/osconfig_v1/services/os_config_service/transports/grpc.py
google/cloud/osconfig_v1/services/os_config_service/transports/grpc_asyncio.py
google/cloud/osconfig_v1/services/os_config_service/transports/rest.py
google/cloud/osconfig_v1/services/os_config_service/transports/rest_base.py
google/cloud/osconfig_v1/services/os_config_zonal_service/__init__.py
google/cloud/osconfig_v1/services/os_config_zonal_service/async_client.py
google/cloud/osconfig_v1/services/os_config_zonal_service/client.py
google/cloud/osconfig_v1/services/os_config_zonal_service/pagers.py
google/cloud/osconfig_v1/services/os_config_zonal_service/transports/__init__.py
google/cloud/osconfig_v1/services/os_config_zonal_service/transports/base.py
google/cloud/osconfig_v1/services/os_config_zonal_service/transports/grpc.py
google/cloud/osconfig_v1/services/os_config_zonal_service/transports/grpc_asyncio.py
google/cloud/osconfig_v1/services/os_config_zonal_service/transports/rest.py
google/cloud/osconfig_v1/services/os_config_zonal_service/transports/rest_base.py
google/cloud/osconfig_v1/types/__init__.py
google/cloud/osconfig_v1/types/inventory.py
google/cloud/osconfig_v1/types/os_policy.py
google/cloud/osconfig_v1/types/os_policy_assignment_reports.py
google_cloud_os_config-1.22.0.dist-info/licenses/LICENSE
google_cloud_os_config-1.22.0.dist-info/METADATA
google_cloud_os_config-1.22.0.dist-info/WHEEL
google_cloud_os_config-1.22.0.dist-info/top_level.txt
google_cloud_os_config-1.22.0.dist-info/RECORD
